emdbg/__init__.py
emdbg/logger.py
emdbg/utils.py
emdbg/analyze/__init__.py
emdbg/analyze/backtrace.py
emdbg/analyze/callgraph.md
emdbg/analyze/callgraph.py
emdbg/analyze/calltrace.md
emdbg/analyze/calltrace.py
emdbg/analyze/hardfault.py
emdbg/analyze/inline.py
emdbg/analyze/priority.py
emdbg/analyze/size.py
emdbg/analyze/utils.py
emdbg/bench/__init__.py
emdbg/bench/fmu.md
emdbg/bench/fmu.py
emdbg/bench/skynode.md
emdbg/bench/skynode.py
emdbg/bench/data/fmu.gdb
emdbg/bench/data/fmu_v5x_orbtrace.cfg
emdbg/bench/data/fmu_v5x_stlink.cfg
emdbg/bench/data/fmu_v6x.jlinkscript
emdbg/bench/data/fmu_v6x_orbtrace.cfg
emdbg/bench/data/fmu_v6x_stlink.cfg
emdbg/debug/__init__.py
emdbg/debug/backend.py
emdbg/debug/crashdebug.md
emdbg/debug/crashdebug.py
emdbg/debug/gdb.md
emdbg/debug/gdb.py
emdbg/debug/jlink.md
emdbg/debug/jlink.py
emdbg/debug/openocd.md
emdbg/debug/openocd.py
emdbg/debug/utils.py
emdbg/debug/data/STM32F765.svd
emdbg/debug/data/STM32H753.svd
emdbg/debug/data/cortex_m.gdb
emdbg/debug/data/jlink.gdb
emdbg/debug/data/openocd.gdb
emdbg/debug/data/orbuculum.gdb
emdbg/debug/px4/__init__.py
emdbg/debug/px4/base.py
emdbg/debug/px4/buffer.py
emdbg/debug/px4/data.py
emdbg/debug/px4/device.py
emdbg/debug/px4/perf.py
emdbg/debug/px4/semaphore.py
emdbg/debug/px4/svd.py
emdbg/debug/px4/system_load.py
emdbg/debug/px4/task.py
emdbg/debug/px4/utils.py
emdbg/debug/remote/__init__.py
emdbg/debug/remote/gdb.py
emdbg/debug/remote/gdb_api_bridge.py
emdbg/debug/remote/mi.py
emdbg/debug/remote/px4.py
emdbg/debug/remote/rpyc.py
emdbg/io/README.md
emdbg/io/__init__.py
emdbg/io/digilent.py
emdbg/patch/README.md
emdbg/patch/__init__.py
emdbg/patch/__main__.py
emdbg/patch/operation.py
emdbg/patch/set.py
emdbg/patch/data/disable_uavcan_v5x.patch
emdbg/patch/data/itm.h
emdbg/patch/data/itm_Make.defs
emdbg/patch/data/itm_nuttx_Makefile.patch
emdbg/patch/data/malloc_return_null.patch
emdbg/patch/data/nuttx_tracing_itm.patch
emdbg/patch/data/nuttx_tracing_itm_uart4.patch
emdbg-1.8.0.dist-info/licenses/LICENSE
emdbg-1.8.0.dist-info/METADATA
emdbg-1.8.0.dist-info/WHEEL
emdbg-1.8.0.dist-info/top_level.txt
emdbg-1.8.0.dist-info/RECORD
