Metadata-Version: 2.4
Name: emdbg
Version: 1.8.0
Summary: Embedded Debug Tools
Author-email: Auterion <success@auterion.com>
License: BSD-3-Clause
Project-URL: Docs, https://auterion.github.io/embedded-debug-tools/emdbg.html
Project-URL: GitHub, https://github.com/auterion/embedded-debug-tools
Project-URL: Changelog, https://github.com/auterion/embedded-debug-tools/blob/main/CHANGELOG.md
Keywords: embedded,debug,gdb,stm32,px4
Classifier: Development Status :: 5 - Production/Stable
Classifier: Environment :: Console
Classifier: Intended Audience :: Developers
Classifier: License :: OSI Approved :: BSD License
Classifier: Operating System :: Unix
Classifier: Programming Language :: Python :: 3.8
Classifier: Topic :: Software Development :: Debuggers
Classifier: Topic :: Software Development :: Embedded Systems
Classifier: Topic :: Software Development :: Testing
Classifier: Topic :: System :: Hardware
Classifier: Topic :: System :: Operating System
Classifier: Topic :: System :: Operating System Kernels
Requires-Python: >=3.8
License-File: LICENSE
Requires-Dist: pyserial<4,>=3.5
Requires-Dist: graphviz<0.21,>=0.20.1
Requires-Dist: pygdbmi<0.12,>=0.11.0.0
Requires-Dist: cmsis-svd==0.4
Requires-Dist: arm-gdb<1,>=0.9.9
Requires-Dist: pydwf<2,>=1.1.19
Requires-Dist: pyelftools>=0.31
Requires-Dist: yoctopuce<2.0,>=1.10.57762
Requires-Dist: rpyc<6,>=5.3.1
Requires-Dist: rich<14,>=13.7.0
Provides-Extra: all
Requires-Dist: pdoc; extra == "all"
Dynamic: license-file
